{"status":"ok","count":"1","count_total":"15","nextpage":"2","posts":[{"vid":"","video_url":"https:\/\/vootvideo.akamaized.net\/s\/enc\/hls\/p\/1982551\/sp\/198255100\/serveFlavor\/entryId\/1_35jgyg64\/v\/1\/pv\/1\/ev\/12\/flavorId\/1_11qbmr4v\/name\/a.mp4\/index.m3u8\/index-v1-a1.m3u8?__hdnea__=st=1615199252~exp=1615285652~acl=\/s\/enc\/hls\/p\/1982551\/sp\/198255100\/serveFlavor\/entryId\/1_35jgyg64\/v\/1\/pv\/1\/ev\/12\/flavorId\/1_*~hmac=fc46132a4bb679323115cebf5b8804b0f51e967a6daa3188fdb064eb1b4111f4","video_title":"Big Win For India Legend","video_thumbnail":"https:\/\/v3img.voot.com\/resizeMedium,w_275,h_154\/v3Storage\/assets\/hl14-1615016399119.jpg","live":"1","user_agent":"","seekto":"","keyurl":""},{"vid":"","video_url":"https:\/\/vootvod.cdn.jio.com\/s\/enc\/hls\/p\/1982551\/sp\/198255100\/serveFlavor\/entryId\/1_f1ze3sgk\/v\/1\/pv\/1\/ev\/12\/flavorId\/1_fuhroz13\/name\/a.mp4\/index.m3u8\/index.m3u8?__hdnea__=st=1615198711~exp=1615285111~acl=\/s\/enc\/hls\/p\/1982551\/sp\/198255100\/serveFlavor\/entryId\/1_f1ze3sgk\/v\/1\/pv\/1\/ev\/12\/flavorId\/1_*~hmac=399f0b6c53541ab15f9a69e6bcdd716723f772aad56a2bebd8020be404c3ec84","video_title":"England Legend vs Bangladesh Legend","video_thumbnail":"https:\/\/v3img.voot.com\/resizeMedium,w_275,h_154\/kimg\/kimg\/bdab878163014c7ba752696ffcd175d9_1280X720.jpg","live":"1","user_agent":"","seekto":"","keyurl":""}]}